anvil/__init__.py
anvil/__version__.py
anvil/cli.py
anvil/api/__init__.py
anvil/api/actors/__init__.py
anvil/api/actors/_animations.py
anvil/api/actors/_component_group.py
anvil/api/actors/_events.py
anvil/api/actors/_render_controller.py
anvil/api/actors/actors.py
anvil/api/actors/components.py
anvil/api/actors/materials.py
anvil/api/actors/spawn_rules.py
anvil/api/biomes/__init__.py
anvil/api/biomes/biomes.py
anvil/api/biomes/components.py
anvil/api/blocks/__init__.py
anvil/api/blocks/blocks.py
anvil/api/blocks/components.py
anvil/api/core/__init__.py
anvil/api/core/camera.py
anvil/api/core/components.py
anvil/api/core/core.py
anvil/api/core/enums.py
anvil/api/core/filters.py
anvil/api/core/sounds.py
anvil/api/core/textures.py
anvil/api/core/types.py
anvil/api/items/__init__.py
anvil/api/items/components.py
anvil/api/items/crafting.py
anvil/api/items/items.py
anvil/api/logic/__init__.py
anvil/api/logic/molang.py
anvil/api/pbr/__init__.py
anvil/api/pbr/pbr.py
anvil/api/ui/__init__.py
anvil/api/ui/dialogue.py
anvil/api/ui/font.py
anvil/api/ui/ui.py
anvil/api/vanilla/__init__.py
anvil/api/vanilla/biomes.py
anvil/api/vanilla/blocks.py
anvil/api/vanilla/effects.py
anvil/api/vanilla/enchantments.py
anvil/api/vanilla/entities.py
anvil/api/vanilla/features.py
anvil/api/vanilla/items.py
anvil/api/world/__init__.py
anvil/api/world/dimensions.py
anvil/api/world/fog.py
anvil/api/world/loot_tables.py
anvil/api/world/particles.py
anvil/api/world/structures.py
anvil/kit/__init__.py
anvil/kit/actors/__init__.py
anvil/kit/actors/materials.py
anvil/kit/world/__init__.py
anvil/kit/world/ldtk.py
anvil/lib/__init__.py
anvil/lib/blockbench.py
anvil/lib/config.py
anvil/lib/format_versions.py
anvil/lib/lib.py
anvil/lib/reports.py
anvil/lib/schemas.py
anvil/lib/templater.py
anvil/lib/translator.py
anvil/templates/__init__.py
mcanvil-0.9.6.1.dist-info/licenses/LICENSE
mcanvil-0.9.6.1.dist-info/METADATA
mcanvil-0.9.6.1.dist-info/WHEEL
mcanvil-0.9.6.1.dist-info/entry_points.txt
mcanvil-0.9.6.1.dist-info/top_level.txt
mcanvil-0.9.6.1.dist-info/RECORD
