Metadata-Version: 2.4
Name: mcanvil
Version: 0.9.6.1
Summary: A Minecraft bedrock content development framework.
Home-page: https://anvil.starktma.net/
Author: Yasser A. Benfoughal
Author-email: yasser@starktma.net
License: GNU GPLv3
Project-URL: Github, https://github.com/StarkTMA/Anvil
Project-URL: Website, https://starktma.net
Project-URL: Twitter, https://twitter.com/StarkTMA_
Platform: Windows
Classifier: Development Status :: 4 - Beta
Classifier: Intended Audience :: Developers
Classifier: Operating System :: Microsoft :: Windows :: Windows 10
Classifier: Operating System :: Microsoft :: Windows :: Windows 11
Classifier: Programming Language :: Python
Classifier: Programming Language :: Python :: 3.10
Classifier: Programming Language :: Python :: 3.11
Classifier: Programming Language :: Python :: 3.12
Classifier: Topic :: Utilities
Requires-Python: >=3.10
License-File: LICENSE
Requires-Dist: commentjson
Requires-Dist: click
Requires-Dist: numpy
Requires-Dist: pillow
Requires-Dist: pygithub
Requires-Dist: deep_translator
Requires-Dist: halo
Requires-Dist: reportlab
Requires-Dist: packaging
Dynamic: license-file
